{
	"Meta(Acqusition)": {
		"doc_id": "REPORT-narration-51001",
		"doc_category": "REPORT",
		"doc_type": "narration",
		"doc_name": "51001_DC_걸어서세계속으로001_2013237087.txt",
		"author": "KBS",
		"publisher": "KBS",
		"publisher_year": "2013",
		"doc_origin": "걸어서세계속으로001"
	},
	"Meta(Refine)": {
		"passage_id": "REPORT-narration-51001-00021",
		"passage": "오케스트라와 피아노 연주, 오페라 등 모든 티켓이 다 있단다.\n나는 빈이 낳고 또 기른 음악가들이 묻혀 있는 시립중앙묘지를 찾았다.\n길이만도 8km에 이르는 큰 묘지로 500만 개가 넘는 묘가 있단다.\n지금 빈 인구의 3배에 가깝다.\n음악가 묘역은 입구 가까운 곳에 있었다.\n평탄한 삶을 살았던 사람보다 역경 속에서도 명곡을 만들어낸 음악가에 더 많은 시선이 가는 것은 어쩔 수 없었다.\n슈베르트는 지병도 있었지만 생활이 어려워 거의 굶어 죽은 것이나 다름없다.\n31살이었다.\n기념비만 서 있는 모차르트도 애틋하다.\n호프부르크 뒤에 있는 모차르트 동상에는 찾는 사람이 끊이지 않지만 그의 죽음에 당시 빈은 무관심했었다.\n모차르트에 대한 아쉬움이 컸던 탓일까.\n베토벤 장례식에는 2만여 명이 모였다.\n운구도 힘들 정도였다고 한다.\n",
		"passage_Cnt": 408
	},
	"Annotation": {
		"summary1": "모차르트에 대한 아쉬움이 컸던 탓인지 베토벤 장례식에는 2만여 명이 모여 운구도 힘들 정도였다.",
		"summary2": "모차르트에 대한 아쉬움이 컸던 탓일까. 베토벤 장례식에는 2만여 명이 모였다. 운구도 힘들 정도였다고 한다.",
		"summary3": null,
		"summary_3_cnt": null
	}
}