{
	"Meta(Acqusition)": {
		"doc_id": "REPORT-minute-00001",
		"doc_category": "REPORT",
		"doc_type": "minute",
		"doc_name": "제19대 국회 교육과학기술위원회 회의록 데이터셋_16481.csv",
		"author": null,
		"publisher": null,
		"publisher_year": null,
		"doc_origin": "국회도서관 포털"
	},
	"Meta(Refine)": {
		"passage_id": "REPORT-minute-00001-00149",
		"passage": "정진후 위원] \"지금 수원여대 감사 진행 중이시지요?\"\n교육과학기술부감사관 박준모] \"예 그렇습니다.\"\n정진후 위원] \"지금 감사 연장이 좀 되었다는 이야기를 들었는데 사실인가요?\"\n교육과학기술부감사관 박준모] \"예 맞습니다.\"\n정진후 위원] \"그러면 거기의 감사 연장을 하게 되신 경위나 배경들을 너무나 잘 아실 것이기 때문에 감사에 만전을 좀 기해 주시고요. 지켜보겠습니다.\"\n교육과학기술부감사관 박준모] \"예 알겠습니다.\"\n정진후 위원] \"그리고 하나만 감사를 하는 수검자 옆에 행정총괄본부장이 늘 배석해서 수검자 옆에 앉아 있다는 사실이 그게 맞습니까?\"\n교육과학기술부감사관 박준모] \"지난주 초에 그런 일이 있어 가지고……\"\n정진후 위원] \"아니 그런 일이 있으면 거기에 계속해서 감사관이 감사를 합니까?\"\n교육과학기술부감사관 박준모] \"아마 시정조치를 해 가지고……\"\n정진후 위원] \"그게 어떻게 감사입니까? 국가 행정기관에서 하는 감사가 그런 형태로 진행돼 가지고 도대체 감사관님들이 어떻게 하시기에 그런 형태의 감사가 지금 진행되지요?\"\n교육과학기술부감사관 박준모] \"그 학교 측에 즉시 시정 요구를 해 가지고 현재는 아마 원만하게 진행이 되고 있는 것으로 그렇게 알고 있습니다.\"\n정진후 위원] \"알겠습니다. 그 부분 감사에 대한 결과는 추후에 관심을 가지고 좀 살펴보겠습니다. 잘못된 것이 있다면 적극적으로 나서서 개선을 해 주셔야 되고……\"\n",
		"passage_Cnt": 706
	},
	"Annotation": {
		"summary1": "정 위원은 수원여대 감사를 진행 중인 교육과학기술부 감사관에게 감사 연장의 경위를 잘 아는 만큼 감사에 만전을 기해달라고 했다. ",
		"summary2": null,
		"summary3": "정진후 위원] \"지금 수원여대 감사 진행 중이시지요?\" 정진후 위원] \"그러면 거기의 감사 연장을 하게 되신 경위나 배경들을 너무나 잘 아실 것이기 때문에 감사에 만전을 좀 기해 주시고요. 교육과학기술부감사관 박준모] \"예 알겠습니다.\"",
		"summary_3_cnt": 134
	}
}