{
	"Meta(Acqusition)": {
		"doc_id": "REPORT-minute-00001",
		"doc_category": "REPORT",
		"doc_type": "minute",
		"doc_name": "제19대 국회 교육과학기술위원회 회의록 데이터셋_16481.csv",
		"author": null,
		"publisher": null,
		"publisher_year": null,
		"doc_origin": "국회도서관 포털"
	},
	"Meta(Refine)": {
		"passage_id": "REPORT-minute-00001-00228",
		"passage": "국가과학기술위원장 김도연] \"예.\"\n박홍근 위원] \"그런데 지금 위원장님께서 보시면 본인이 보유하고 있는 기업의 주식 중에서 또는 배우자나 장남이 갖고 있는 주식 중에서 이런 과학기술 관련된 주식이 꽤 있습니다. 알고 계시지요?\"\n국가과학기술위원장 김도연] \"예.\"\n박홍근 위원] \"국과위는 말 그대로 연구개발의 성과를 평가하고 또 관련된 예산을 배분하는 그런 권한을 갖고 있는 조직입니다. 그렇지요?\"\n국가과학기술위원장 김도연] \"예.\"\n박홍근 위원] \"제가 확인해 보니까 지금 이것은 공직자 재산 자료를 제가 살펴본 겁니다.   위원장께서는 본인과 배우자 명의로 주식거래를 한 OCI사와 그다음에 2006년부터 오히려 재임 전부터 주식을 보유해 온 나노스퀘어 이 2개 업체의 주식을 갖고 계셨다가 파셨거나 아니면 아직도 보유를 하고 계시지요?\"\n국가과학기술위원장 김도연] \"지금 현재는 보유하고 있지 않습니다.\"\n박홍근 위원] \"아니 그러니까 작년 11월에 OCI 주식을 매입했다가 2월 달에 팔았고요. 그렇지요?\"\n국가과학기술위원장 김도연] \"그렇습니다.\"\n박홍근 위원] \"그리고 나노스퀘어 같은 경우는 아직 지금 비상장 주식이기 때문에 보유하고 계신 것 아닙니까?\"\n국가과학기술위원장 김도연] \"그렇습니다.\"\n박홍근 위원] \"예 그렇지요.  그런데 이 OCI 주식 같은 경우 말입니다 우선 이 OCI에 대해서 2009년부터 2015년도까지 지원된 예산이 R&D 사업으로 얼마인지 알고 계십니까?\"\n",
		"passage_Cnt": 730
	},
	"Annotation": {
		"summary1": "김 국가 과학기술 위원장은 본인과 배우자 명의로 주식거래를 한 OCI사와 나노스퀘어 업체의 주식을 보유하냐는 박 위원의 질문에 아니라고 답했다.",
		"summary2": null,
		"summary3": "박홍근 위원] \"제가 확인해 보니까 지금 이것은 공직자 재산 자료를 제가 살펴본 겁니다. 위원장께서는 본인과 배우자 명의로 주식거래를 한 OCI사와 그다음에 2006년부터 오히려 재임 전부터 주식을 보유해 온 나노스퀘어 이 2개 업체의 주식을 갖고 계셨다가 파셨거나 아니면 아직도 보유를 하고 계시지요?\" 국가과학기술위원장 김도연] \"지금 현재는 보유하고 있지 않습니다.\"",
		"summary_3_cnt": 210
	}
}