{
	"Meta(Acqusition)": {
		"doc_id": "REPORT-literature-01246",
		"doc_category": "REPORT",
		"doc_type": "literature",
		"doc_name": "회(懷)",
		"author": "채만식",
		"publisher": null,
		"publisher_year": null,
		"doc_origin": "저작권위원회"
	},
	"Meta(Refine)": {
		"passage_id": "REPORT-literature-01246-01246",
		"passage": " 그러니 화통이 그 녀석이 그만큼이나 기운이 셀 지경이면, 우리게 남산이라도 정통으로 칵 한번 들이받는다면, 단박에 구멍이 뻥하니 맞창이 뚫어지고 말 것 같았다. 날래기는 또 어찌 그리 날래며…… 눈 깜짝할 동안인데 어느 겨를에 저 편 산모룽이에 가 서서는 흙을 푸고 섰고. 나는 새도 못 따른다더니 참 그런 성 불렀다.\n그렇게 날랜 놈이니 한바탕 타고 내달린다면, 약간 자행거 꽁무니나 타보던 맛하고는 어림도 아니요. 사람이 금세 날개가 돋힌 듯 시원하고 고숩고, 천하 그런 재밌을 데라곤 없으련 싶었다. 대가리 굵은 학도들이 연방 임(任)×× 선생을 졸라대는 것이었었다. 어서 말을 해서 차를 좀 태워 달라고. 물론들, 차를 타보고 싶은 것도 타보고 싶은 것이지만 한편으로는 임×× 선생을 끕끕수를 주자는 노릇이었었다. 이 임×× 선생이라는 이가, 시방은 근처의 다른 학교에서 버젓하니 교장까지 되어가지고, 그만큼 관록도 생기고, 다 점잖도 하고, 또한 더러 만난다치면 깜박 서로 반갑기도 하고 한 터이지만, 처음 그때 우리 학교로 와서 한동안은 지질한 못난이 구실을 했었다. 임×× 선생 두루마기 같다는 별명이 생길 만큼 유명한 그 무르팍 지는 돔방 두루마기를 입고, 괜시리 한 손으로 상고머리한 귀 뒤를 만질락 말락 해싸면서 “애─애─, 나는 애─, 이 사람은 애─, 충청도 서천서 오났는데, 애─, 임××라는 사람인데 애─, 아무 것두 모르는 사람인대, 애─, 아무 것두 모르는 사람인대, 애!” 이것이 그가 전교 학도들 앞에 나서서 부임한 인사를 하느라고 하던 거동이었었다.\n",
		"passage_Cnt": 776
	},
	"Annotation": {
		"summary1": "임 선생은 근처 학교에서 교장이 되었지만 처음 우리 학교에 와서는 지질한 못난이 구실을 해 학도들이 임 선생에게 끕끕수를 주자는 노릇으로 졸라댔다.",
		"summary2": "대가리 굵은 학도들이 연방 임(任)×× 선생을 졸라대는 것이었었다. 물론들, 차를 타보고 싶은 것도 타보고 싶은 것이지만 한편으로는 임×× 선생을 끕끕수를 주자는 노릇이었었다.  이 임×× 선생이라는 이가, 시방은 근처의 다른 학교에서 버젓하니 교장까지 되어가지고, 그만큼 관록도 생기고, 다 점잖도 하고, 또한 더러 만난다치면 깜박 서로 반갑기도 하고 한 터이지만, 처음 그때 우리 학교로 와서 한동안은 지질한 못난이 구실을 했었다.",
		"summary3": null,
		"summary_3_cnt": null
	}
}