{
	"Meta(Acqusition)": {
		"doc_id": "REPORT-minute-00002",
		"doc_category": "REPORT",
		"doc_type": "minute",
		"doc_name": "제19대 국회 교육문화체육관광위원회 회의록 데이터셋.csv",
		"author": null,
		"publisher": null,
		"publisher_year": null,
		"doc_origin": "국회도서관 포털"
	},
	"Meta(Refine)": {
		"passage_id": "REPORT-minute-00002-00524",
		"passage": "한국연구재단이사장 이승종] \"그렇습니다.\"\n이에리사 위원] \"이사장님 조금 더 검토를……\"\n한국연구재단이사장 이승종] \"그래서 실제로 이런 상황들이 사전에 예방될 수 있는 것이 중요하다고 생각돼서 관련된 교육 프로그램이라든가 이런 것도 저희가 지속적으로 해 나가고 있습니다.\"\n이에리사 위원] \"심사를 조금 더 엄격하게 해야 된다든지 아니면 한 사람이 반납했을 경우에는 그다음에 다시 한번 기회를 안 준다든지 뭔가 제도가 보완되면 어떨까 하는 생각이 듭니다.\"\n한국연구재단이사장 이승종] \"현재 최대 참여 제한을 5년까지 그런 제재조치도 하고 있습니다.\"\n이에리사 위원] \"예.  우리 창의재단 이사장님 창의재단 홈페이지에 보면 지금 23페이지 보니까 오늘 업무보고에서도 체계적으로 해서 학생들의 역량을 키울 수 있는 창의교육 콘텐츠와 수업모델을 지속적으로 개발하겠다라는 얘기를 하셨거든요. 그런데 그게 어떤 내용인지 잠깐 간단하게 한번……\"\n한국과학창의재단이사장 강혜련] \"우리가 ‘crezone.net’이라고 그러는데 창의인성 교육넷은 지금 학교 현장에서 학생들이 창의적 체험활동을 비교과로 해야 되는 부분이 있는데 그러면 학교 밖의 다양한 체험장을 가야 되는데 사실은 정보가 없습니다 학교를 나오면 어디로 가야 되는지. 그래서 우리가 학생들이 갈 수 있는 곳이 기업이 됐든 공공기관이 됐든 그런 어떤 창의적 체험활동의 리소스(resource)를 다 모아 놓고 정보를 제공하는 사이트입니다.\"\n",
		"passage_Cnt": 726
	},
	"Annotation": {
		"summary1": "이 한국연구재단 이사장은 실제 상황이 사전에 예방될 수 있도록 관련 교육 프로그램 등을 지속적으로 하고 있으며 최대 참여 제한도 5년으로 제재하고 있다고 했다.",
		"summary2": "한국연구재단이사장 이승종] \"그래서 실제로 이런 상황들이 사전에 예방될 수 있는 것이 중요하다고 생각돼서 관련된 교육 프로그램이라든가 이런 것도 저희가 지속적으로 해 나가고 있습니다.\" 한국연구재단이사장 이승종] \"현재 최대 참여 제한을 5년까지 그런 제재조치도 하고 있습니다.\"",
		"summary3": null,
		"summary_3_cnt": null
	}
}