{
	"Meta(Acqusition)": {
		"doc_id": "REPORT-edit-30221",
		"doc_category": "REPORT",
		"doc_type": "edit",
		"doc_name": "우리나라에 불교를 처음 들여온 허황옥",
		"author": null,
		"publisher": null,
		"publisher_year": null,
		"doc_origin": "월간조선"
	},
	"Meta(Refine)": {
		"passage_id": "REPORT-edit-30221-00006",
		"passage": " 《삼국유사》 ‘가락국기’ 중 김질왕(金王)에 대한 기사에는 다음과 같은 내용이 나온다.\n 〈시조 수로왕의 8대손 김질왕은 부지런하게 나라를 다스렸으며, 매우 도를 숭상하여 시조모(始祖母) 허황후를 위해 명복을 빌고자 하여 원가(元嘉) 29년 임진(452년)에 수로왕과 허황후가 결혼한 곳에 절을 세우고 액자에 ‘왕후사(王后寺)’라 했다.〉\n 이처럼 김질왕 때 시조모를 위해 ‘왕후사’를 세웠다는 것은, 허황옥이 불교 신봉자였음을 간접적으로 보여주고 있는 대목이라고 할 수 있다.\n 또한 김수로왕이 당시 불교를 봉행했을 것으로 추측할 수 있는 기사가 《삼국유사》 탑상편 ‘어산의 부처 영상’에도 보인다.\n 〈옛날 하늘에서 알이 바닷가로 내려와 사람이 되어 나라를 다스렸는데, 곧 수로왕이다. 이때 그 영토 안에 옥지(玉池)가 있었고, 그 못 안에는 독룡이 살았다. 만어산에 다섯 나찰녀(羅刹女)가 있어, 그 독룡과 오가며 사귀었다. 그러므로 때때로 뇌우(雷雨)를 내려 4년 동안 오곡이 결실을 맺지 못했다. 왕은 주술(呪術)로써 이 일을 금하려 해도 할 수 없으므로, 머리 숙여 부처를 청하여 설법을 했다. 그랬더니 그제야 나찰녀가 오계(五戒)를 받았으며, 그 이후로는 재해가 없었다.〉\n 이 기록에 보이는 ‘왕이 부처를 청하여 설법을 했다’는 것은, 이 또한 가락국 초창기에 이미 김수로왕까지도 불교를 신봉했음을 여실히 보여주고 있는 대목이 아닐 수 없다.\n",
		"passage_Cnt": 705
	},
	"Annotation": {
		"summary1": "삼국유사의 가락국기 중에는 허 씨가 불교 신봉자였음을 간접적으로 보여주고 있는 대목이 나오며 탑상편에는 김수로왕이 불교를 봉행했을 것으로 추측할 수 있는 기사가 보인다.",
		"summary2": null,
		"summary3": "《삼국유사》 ‘가락국기’ 중 김질왕(金王)에 대한 기사에는 다음과 같은 내용이 나온다. 이처럼 김질왕 때 시조모를 위해 ‘왕후사’를 세웠다는 것은, 허황옥이 불교 신봉자였음을 간접적으로 보여주고 있는 대목이라고 할 수 있다. 또한 김수로왕이 당시 불교를 봉행했을 것으로 추측할 수 있는 기사가 《삼국유사》 탑상편 ‘어산의 부처 영상’에도 보인다.",
		"summary_3_cnt": 195
	}
}