{
	"Meta(Acqusition)": {
		"doc_id": "REPORT-speech-00063",
		"doc_category": "REPORT",
		"doc_type": "speech",
		"doc_name": "속기자료 12쪽 (17).hwp",
		"author": null,
		"publisher": null,
		"publisher_year": null,
		"doc_origin": "문화체육관광부 정책브리핑 포털"
	},
	"Meta(Refine)": {
		"passage_id": "REPORT-speech-00063-00005",
		"passage": "다음은 교육·보육 종사자와 돌봄인력에 대한 7월 예방접종 사전예약에 대해서 말씀드리도록 하겠습니다. 사전 예약대상은 초등학교 3학년에서 6학년 및 중학교 교직원과 앞선 조기접종, 즉 7월 13일에서 17일 사이를 뜻합니다. 조기접종에 참여하지 않은 어린이집, 유치원 및 초등학교 1·2학년 교직원 등 교육 및 보육 종사자, 돌봄인력 등입니다. 사전예약은 7월 14일 0시부터 17일 18시까지 실시되며, 1차 접종은 7월 28일 수요일부터 8월 7일까지 진행됩니다. 접종 백신은 화이자 백신이며, 접종을 희망하시는 분은 코로나19 예방접종 사전예약 누리집에서 방문 가능한 접종기관을 선택하여 접종일정을 예약하실 수 있습니다. 다수의 학생들은 백신 예방접종 대상이 아니므로 2학기 전면등교를 위해서는 교직원들 한 분, 한 분의 접종이 절실한 상황입니다. 접종에 적극 참여해 주시기를 당부드립니다. QR 체크인을 통한 예방접종 증명방법에 대해서 말씀드리겠습니다. 지난 7월 12일부터 전자출입기록, 즉 QR 체크인 시 예방접종 증명이 동시에 확인되는 시스템이 가동 중입니다. 네이버, 카카오, 이런 통신 3사의 인증과 토스 앱을 통한 예방접종 증명이 가능합니다. 통합 QR은 기존의 QR 체크인과 같은 방법으로 사용하면 되고, 인증 시 화면 메시지와 음성으로 접종 회차와 예방접종 정보가 확인됩니다. 백신 수급상황에 대해서 말씀드리겠습니다. 개별 계약된 화이자 백신 79만 9,000회분이 7월 14일 인천공항에 도착합니다. 더 많은 분들이 빠르고 안전하게 예방접종을 받을 수 있도록 최선의 노력을 다하겠습니다.",
		"passage_Cnt": 788
	},
	"Annotation": {
		"summary1": "교육·보육 종사자와 돌봄인력에 대한 예방접종에 쓰이는 백신은 화이자 백신으로 접종을 희망하는 사람은 코로나19 예방접종 사전예약 누리집을 통해 접종기관과 일정을 선택하면 된다.",
		"summary2": null,
		"summary3": "다음은 교육·보육 종사자와 돌봄인력에 대한 7월 예방접종 사전예약에 대해서 말씀드리도록 하겠습니다. 접종 백신은 화이자 백신이며, 접종을 희망하시는 분은 코로나19 예방접종 사전예약 누리집에서 방문 가능한 접종기관을 선택하여 접종일정을 예약하실 수 있습니다.",
		"summary_3_cnt": 145
	}
}